setup.py
distributions_test11/Binomialdistribution.py
distributions_test11/Gaussiandistribution.py
distributions_test11/Generaldistribution.py
distributions_test11/__init__.py
distributions_test11.egg-info/PKG-INFO
distributions_test11.egg-info/SOURCES.txt
distributions_test11.egg-info/dependency_links.txt
distributions_test11.egg-info/not-zip-safe
distributions_test11.egg-info/top_level.txt